calculator_meluzx/__init__.py
calculator_meluzx/calculator_meluzx.py
calculator_meluzx-0.0.8.dist-info/LICENSE
calculator_meluzx-0.0.8.dist-info/METADATA
calculator_meluzx-0.0.8.dist-info/WHEEL
calculator_meluzx-0.0.8.dist-info/top_level.txt
calculator_meluzx-0.0.8.dist-info/RECORD
