Metadata-Version: 2.1
Name: calculator_meluzx
Version: 0.0.8
Summary: Calculator with addition, subtraction, multiplication, division and (n) root functions
Home-page: https://github.com/TuringCollegeSubmissions/muzgir-DWWP.1.5?tab=readme-ov-file
Author: Milita Uzgiryte
Author-email: milita713@gmail.com
Classifier: Programming Language :: Python :: 3
Classifier: License :: OSI Approved :: MIT License
Classifier: Operating System :: OS Independent
Requires-Python: >=3.6
License-File: LICENSE
